micropackage/__init__.py
micropackage/big_brain_code.py
micropackage/py.typed
microtraining-1.0.0.dist-info/licenses/LICENSE
microtraining-1.0.0.dist-info/METADATA
microtraining-1.0.0.dist-info/WHEEL
microtraining-1.0.0.dist-info/top_level.txt
microtraining-1.0.0.dist-info/RECORD
