Metadata-Version: 2.4
Name: microtraining
Version: 1.0.0
Summary: Hans provides solutions. Always.
Author: Alexander Nasuta
Author-email: Alexander Nasuta <alexander.nasuta@ima.rwth-aachen.de>
License: MIT License
Project-URL: Homepage, https://github.com/Alexander-Nasuta/microtraining
Keywords: micro,training,big,brain,1337
Platform: unix
Platform: linux
Platform: osx
Platform: cygwin
Platform: win32
Classifier: License :: OSI Approved :: MIT License
Classifier: Programming Language :: Python
Classifier: Programming Language :: Python :: 3
Requires-Python: >=3.11
License-File: LICENSE
Requires-Dist: requests<3,>=2
Provides-Extra: dev
Requires-Dist: pip-tools; extra == "dev"
Requires-Dist: pytest; extra == "dev"
Requires-Dist: pytest-cov; extra == "dev"
Requires-Dist: mypy; extra == "dev"
Requires-Dist: flake8; extra == "dev"
Requires-Dist: tox; extra == "dev"
Requires-Dist: twine; extra == "dev"
Dynamic: license-file
